iqm/data_definitions/__init__.py
iqm/data_definitions/descriptor_set.bin
iqm/data_definitions/py.typed
iqm/data_definitions/common/__init__.py
iqm/data_definitions/common/v1/__init__.py
iqm/data_definitions/common/v1/channel_properties_pb2.py
iqm/data_definitions/common/v1/channel_properties_pb2.pyi
iqm/data_definitions/common/v1/data_types_pb2.py
iqm/data_definitions/common/v1/data_types_pb2.pyi
iqm/data_definitions/common/v1/observation_pb2.py
iqm/data_definitions/common/v1/observation_pb2.pyi
iqm/data_definitions/common/v1/parameter_pb2.py
iqm/data_definitions/common/v1/parameter_pb2.pyi
iqm/data_definitions/common/v1/playlist_pb2.py
iqm/data_definitions/common/v1/playlist_pb2.pyi
iqm/data_definitions/common/v1/setting_pb2.py
iqm/data_definitions/common/v1/setting_pb2.pyi
iqm/data_definitions/common/v1/spot_result_pb2.py
iqm/data_definitions/common/v1/spot_result_pb2.pyi
iqm/data_definitions/common/v1/struct_pb2.py
iqm/data_definitions/common/v1/struct_pb2.pyi
iqm/data_definitions/common/v1/sweep_pb2.py
iqm/data_definitions/common/v1/sweep_pb2.pyi
iqm/data_definitions/station_control/__init__.py
iqm/data_definitions/station_control/v1/__init__.py
iqm/data_definitions/station_control/v1/run_definition_pb2.py
iqm/data_definitions/station_control/v1/run_definition_pb2.pyi
iqm/data_definitions/station_control/v1/sweep_request_pb2.py
iqm/data_definitions/station_control/v1/sweep_request_pb2.pyi
iqm/data_definitions/station_control/v1/task_service_pb2.py
iqm/data_definitions/station_control/v1/task_service_pb2.pyi
iqm/data_definitions/station_control/v2/__init__.py
iqm/data_definitions/station_control/v2/run_definition_pb2.py
iqm/data_definitions/station_control/v2/run_definition_pb2.pyi
iqm/data_definitions/station_control/v2/task_service_pb2.py
iqm/data_definitions/station_control/v2/task_service_pb2.pyi
iqm/models/__init__.py
iqm/models/py.typed
iqm/models/channel_properties/__init__.py
iqm/models/channel_properties/channel_properties.py
iqm_data_definitions-2.21.dist-info/licenses/LICENSE.txt
iqm_data_definitions-2.21.dist-info/METADATA
iqm_data_definitions-2.21.dist-info/WHEEL
iqm_data_definitions-2.21.dist-info/top_level.txt
iqm_data_definitions-2.21.dist-info/RECORD
