Metadata-Version: 2.4
Name: iqm-data-definitions
Version: 2.21
Summary: Common repository for data definitions inside IQM
Author-email: IQM Finland Oy <developers@meetiqm.com>
License:                                  Apache License
Project-URL: Homepage, https://pypi.org/project/iqm-data-definitions/
Project-URL: Documentation, https://iqm-finland.github.io/docs/
Classifier: Development Status :: 4 - Beta
Classifier: Programming Language :: Python :: 3 :: Only
Classifier: Topic :: Scientific/Engineering :: Physics
Classifier: Intended Audience :: Science/Research
Requires-Python: >=3.11.0
License-File: LICENSE.txt
Requires-Dist: protobuf<5.0,>=4.25.3
Requires-Dist: types-protobuf
Requires-Dist: numpy<3.0,>=1.26.4
Requires-Dist: scipy<1.16.2,>=1.11.4
Requires-Dist: scipy-stubs
Provides-Extra: testing
Requires-Dist: pytest==7.4.0; extra == "testing"
Requires-Dist: pytest-cov==4.1.0; extra == "testing"
Requires-Dist: mypy==1.18.2; extra == "testing"
Requires-Dist: ruff==0.13.1; extra == "testing"
Provides-Extra: docs
Requires-Dist: sphinx==7.2.6; extra == "docs"
Requires-Dist: sphinx-book-theme==1.1.2; extra == "docs"
Provides-Extra: cicd
Requires-Dist: build[virtualenv]==1.3.0; extra == "cicd"
Requires-Dist: tox==4.30.2; extra == "cicd"
Requires-Dist: tox-current-env; extra == "cicd"
Requires-Dist: twine==6.2.0; extra == "cicd"
Requires-Dist: importlib-metadata==8.7.0; extra == "cicd"
Requires-Dist: python-gitlab==3.2.0; extra == "cicd"
Requires-Dist: packaging==25.0; extra == "cicd"
Requires-Dist: mypy-protobuf==3.6.0; extra == "cicd"
Dynamic: license-file
